odoo/addons/web_widget_product_label_section_and_note_full_label/README.rst
odoo/addons/web_widget_product_label_section_and_note_full_label/__init__.py
odoo/addons/web_widget_product_label_section_and_note_full_label/__manifest__.py
odoo/addons/web_widget_product_label_section_and_note_full_label/i18n/it.po
odoo/addons/web_widget_product_label_section_and_note_full_label/i18n/web_widget_product_label_section_and_note_full_label.pot
odoo/addons/web_widget_product_label_section_and_note_full_label/readme/CONTRIBUTORS.md
odoo/addons/web_widget_product_label_section_and_note_full_label/readme/DESCRIPTION.md
odoo/addons/web_widget_product_label_section_and_note_full_label/static/description/icon.png
odoo/addons/web_widget_product_label_section_and_note_full_label/static/description/index.html
odoo/addons/web_widget_product_label_section_and_note_full_label/static/src/product_label_section_and_note_field/product_label_section_and_note_field.esm.js
odoo/addons/web_widget_product_label_section_and_note_full_label/static/src/product_label_section_and_note_field/product_label_section_and_note_field.xml
odoo_addon_web_widget_product_label_section_and_note_full_label-18.0.1.0.0.3.dist-info/METADATA
odoo_addon_web_widget_product_label_section_and_note_full_label-18.0.1.0.0.3.dist-info/WHEEL
odoo_addon_web_widget_product_label_section_and_note_full_label-18.0.1.0.0.3.dist-info/top_level.txt
odoo_addon_web_widget_product_label_section_and_note_full_label-18.0.1.0.0.3.dist-info/RECORD
